wikiwormhole/__init__.py
wikiwormhole/title2vec.py
wikiwormhole/wikiapi.py
wikiwormhole/traverse/popular.py
wikiwormhole/traverse/similar.py
wikiwormhole/traverse/traverse.py
wikiwormhole/util/fixedpq.py
wikiwormhole/util/graph.py
wikiwormhole/util/sinkset.py
wikiwormhole-0.0.4.data/scripts/setup_wormhole.py
wikiwormhole-0.0.4.dist-info/LICENSE
wikiwormhole-0.0.4.dist-info/METADATA
wikiwormhole-0.0.4.dist-info/WHEEL
wikiwormhole-0.0.4.dist-info/top_level.txt
wikiwormhole-0.0.4.dist-info/RECORD
