Metadata-Version: 2.1
Name: wikiwormhole
Version: 0.0.4
Summary: A library for finding the link between two wikipedia pages.
Author: Jason Pittman
Author-email: "jspencerpittman@gmail.com"
Requires-Python: >=3.6
License-File: LICENSE
Requires-Dist: gensim <4.4.0,>=4.3.0
Requires-Dist: nltk <3.9.0,>=3.8
Requires-Dist: numpy
Requires-Dist: pywikibot <9.1.0,>=9.0
Requires-Dist: requests
Requires-Dist: PyYaml <6.1.0,>=6.0
Requires-Dist: scipy <1.13.0,>=1.12.0
